{
	"ID":"0400",
	"NAME":"미사일 컨테이너",
	"ICON_PATH":"ReplaceableTextures/CommandButtons/BTNClusterRockets.png",
	"TIER":"4",
	"COST":"4",
	"CAST_TYPE":"CONFIG_CAST_TYPE_TARGET_LOCATION",
	"TAG1":"CONFIG_ABILITY_TAG_FIREARM",
	"TAG2":"CONFIG_ABILITY_TAG_EXPLOSION",
	"TAG3":"null",
	"TAG4":"null",
	"DELAY":"0.2",
	"RANGE":"1200.0",
	"BACKSWING":"0.15",
	"RADIUS2":"65.0",
	"RADIUS3":"500.0",
	"STARTAT":"32.5",
	"VELO":"400.0",
	"INTERVAL":"0.125",
	"COUNT":"20",
	"IS_WEAPON":"false",
	"DAMAGE_SECONDARY":"0.3",
	"DAMAGE_PER_LEVEL":"0.2",
	"DAMAGE_AMPLIFIER1":"1.25",
	"DAMAGE_STAT1":"CONFIG_STAT_ATTACK",
	"STAT_BONUS1":"CONFIG_STAT_ATTACK",
	"STAT_BONUS2":"CONFIG_STAT_SPELL_BOOST"
}